EasyDatabase/__init__.py
EasyDatabase-2.1.dist-info/LICENSE
EasyDatabase-2.1.dist-info/METADATA
EasyDatabase-2.1.dist-info/WHEEL
EasyDatabase-2.1.dist-info/top_level.txt
EasyDatabase-2.1.dist-info/RECORD
