Metadata-Version: 2.1
Name: EasyDatabase
Version: 2.1
Summary: A database that is very easy to set up and use
Home-page: https://github.com/shaunikm/EasyDB
Author: Shaunik Musukula
Author-email: shaunik.musukula@gmail.com
License: UNKNOWN
Platform: UNKNOWN
Classifier: Programming Language :: Python :: 3
Classifier: License :: OSI Approved :: MIT License
Classifier: Operating System :: OS Independent
Requires-Python: >=3.6
